sanda/__init__.py
sanda/api/__init__.py
sanda/cli/__init__.py
sanda/cli/entry.py
sanda/core/__init__.py
sanda/utils/__init__.py
sanda/web/__init__.py
tests/__init__.py
tests/api/__init__.py
tests/cli/__init__.py
tests/cli/test_entry.py
tests/core/__init__.py
tests/utils/__init__.py
tests/web/__init__.py
sanda-0.0.2.dist-info/LICENSE
sanda-0.0.2.dist-info/METADATA
sanda-0.0.2.dist-info/WHEEL
sanda-0.0.2.dist-info/entry_points.txt
sanda-0.0.2.dist-info/top_level.txt
sanda-0.0.2.dist-info/RECORD
